django_mlops/__init__.py
django_mlops/admin.py
django_mlops/apps.py
django_mlops/models.py
django_mlops/task_utils.py
django_mlops/tasks_db.py
django_mlops/tests.py
django_mlops/urls.py
django_mlops/views.py
django_mlops/migrations/0001_initial.py
django_mlops/migrations/0002_processtask_task_output.py
django_mlops/migrations/0003_process_alter_processtask_unique_together_and_more.py
django_mlops/migrations/0004_processtask_nested_task.py
django_mlops/migrations/0005_rename_nested_task_processtask_bidirectional_task.py
django_mlops/migrations/0006_remove_processtask_bidirectional_task_and_more.py
django_mlops/migrations/0007_rename_bidirectional_dependencies_processtask_depends_bidirectionally_with.py
django_mlops/migrations/0008_rename_dependencies_processtask_depends_on.py
django_mlops/migrations/0009_processrun_taskrun.py
django_mlops/migrations/0010_processtask_nested.py
django_mlops/migrations/0011_processrun_process_complete_taskrun_task_complete.py
django_mlops/migrations/0012_process_process_display_name_and_more.py
django_mlops/migrations/0013_remove_taskrun_task_snapshot_and_more.py
django_mlops/migrations/0014_taskrun_task_snapshot_id_alter_taskrun_task.py
django_mlops/migrations/0015_alter_taskrun_output.py
django_mlops/migrations/0016_rename_processrun_executedprocess_and_more.py
django_mlops/migrations/0017_executedtask_task_snapshot_and_more.py
django_mlops/migrations/0018_process_in_current_code_base_and_more.py
django_mlops/migrations/0019_executedprocess_process_id_snapshot_and_more.py
django_mlops/migrations/0020_executedtask_task_name_snapshot.py
django_mlops/migrations/0021_alter_executedprocess_process_id_snapshot_and_more.py
django_mlops/migrations/0022_executedprocess_status.py
django_mlops/migrations/0023_mlresult.py
django_mlops/migrations/0024_alter_mlresult_executed_process.py
django_mlops/migrations/0025_executedprocess_last_checkpoint_datetime.py
django_mlops/migrations/0026_executedprocess_exceptions_and_more.py
django_mlops-0.1.2.dist-info/LICENSE
django_mlops-0.1.2.dist-info/WHEEL
django_mlops-0.1.2.dist-info/METADATA
django_mlops-0.1.2.dist-info/RECORD
