Metadata-Version: 2.1
Name: django_mlops
Version: 0.1.2
Summary: A Django app for MLOps: eliminate unnecessary duplication of tools and project complexity
Keywords: django,mlops
Author-email: Your Name <eburmicz@gmail.com>
Requires-Python: >=3.9
Classifier: Framework :: Django
Classifier: Programming Language :: Python :: 3
Classifier: License :: OSI Approved :: MIT License
Classifier: Operating System :: OS Independent
Requires-Dist: Django>=5
Project-URL: Homepage, https://github.com/eddyojb88/django_mlops
